{
  "user": [
    {
      "id": "0c79",
      "firstName": "test",
      "lastName": "user1",
      "email": "testuser1@example.com",
      "telephone": "1111111111",
      "county": "Kiambu",
      "experience": "Red Cross",
      "password": "1",
      "confirmPassword": "1",
      "terms": true,
      "applications": [
        {
          "opportunityId": "1",
          "opportunityTitle": "Volunteer Coordinator",
          "opportunityDescription": "Help organize and coordinate volunteer efforts.",
          "applicationDate": "2024-11-14T07:03:32.775Z"
        },
        {
          "opportunityId": "1",
          "opportunityTitle": "Volunteer Coordinator",
          "opportunityDescription": "Help organize and coordinate volunteer efforts.",
          "applicationDate": "2024-11-14T11:59:32.672Z"
        },
        {
          "opportunityId": "1",
          "opportunityTitle": "Volunteer Coordinator",
          "opportunityDescription": "Help organize and coordinate volunteer efforts.",
          "applicationDate": "2024-11-14T12:05:34.140Z"
        },
        {
          "opportunityId": "1",
          "opportunityTitle": "Volunteer Coordinator",
          "opportunityDescription": "Help organize and coordinate volunteer efforts.",
          "applicationDate": "2024-11-14T12:51:05.371Z"
        },
        {
          "opportunityId": "1",
          "opportunityTitle": "Volunteer Coordinator",
          "opportunityDescription": "Help organize and coordinate volunteer efforts.",
          "applicationDate": "2024-11-14T13:34:54.200Z"
        }
      ]
    },
    {
      "id": "c250",
      "firstName": "Kevin",
      "lastName": "Daniel",
      "email": "prodigy4614@gmail.com",
      "telephone": "0707759220",
      "county": "Kiambu",
      "experience": "Red Cross",
      "password": "1",
      "confirmPassword": "1",
      "terms": true
    },
    {
      "id": "c8f4",
      "firstName": "Felister",
      "lastName": "Kiragu",
      "email": "kiragufelister18@gmail.com",
      "telephone": "0112130739",
      "county": "nairobi",
      "experience": "experienced",
      "password": "1",
      "confirmPassword": "1",
      "terms": true
    },
    {
      "id": "8961",
      "firstName": "Felister",
      "lastName": "Kiragu",
      "email": "felister.kiragu@student.moringaschool.com",
      "telephone": "0112130739",
      "county": "nairobi",
      "experience": "experienced",
      "password": "1",
      "confirmPassword": "1",
      "terms": true
    },
    {
      "id": "8caa",
      "firstName": "Felister",
      "lastName": "Kiragu",
      "email": "felister.kiragu@student.moringaschool.com",
      "telephone": "0112130739",
      "county": "nairobi",
      "experience": "experienced",
      "password": "2",
      "confirmPassword": "2",
      "terms": true
    },
    {
      "id": "47a1",
      "firstName": "Felister",
      "lastName": "Kiragu",
      "email": "kiragufelister18@gmail.com",
      "telephone": "0112130739",
      "county": "nairobi",
      "experience": "experienced",
      "password": "1",
      "confirmPassword": "1",
      "terms": true
    },
    {
      "id": "8151",
      "firstName": "Mary",
      "lastName": "Njeri",
      "email": "mary@gmail.com",
      "telephone": "1234567890",
      "county": "kiambu",
      "experience": "java",
      "password": "10",
      "confirmPassword": "10",
      "terms": true
    },
    {
      "id": "839e",
      "firstName": "Mary",
      "lastName": "Njeri",
      "email": "mary@gmail.com",
      "telephone": "1234567890",
      "county": "kiambu",
      "experience": "mary@gmail.com",
      "password": "10",
      "confirmPassword": "10",
      "terms": true
    }
  ],
  "organization": [
    {
      "id": "3876",
      "organizationName": "testorganization1",
      "email": "testorg1@example.com",
      "telephone": "1111111111",
      "website": "https://test.org2.com",
      "password": "1",
      "confirmPassword": "1",
      "terms": true,
      "volunteerOpportunities": [
        {
          "id": "1",
          "title": "Volunteer Coordinator",
          "description": "Help organize and coordinate volunteer efforts.",
          "location": "Nairobi, Kenya"
        }
      ]
    },
    {
      "id": "0b44",
      "organizationName": "baristars",
      "email": "mary@gmail.com",
      "telephone": "1234567890",
      "website": "baristars",
      "password": "10",
      "confirmPassword": "10",
      "terms": true
    },
    {
      "id": "6036",
      "organizationName": "baristars",
      "email": "baristars@gmail.com",
      "telephone": "1234567890",
      "website": "baristars",
      "password": "11",
      "confirmPassword": "11",
      "terms": true
    },
    {
      "id": "4bff",
      "organizationName": "baristars",
      "email": "baristars@gmail.com",
      "telephone": "1234567890",
      "website": "baristars@gmail.com",
      "password": "11",
      "confirmPassword": "11",
      "terms": true
    }
  ],
  "contactus": []
  "contactus": []
}